darkcoins/__init__.py
darkcoins/base/__init__.py
darkcoins/base/db/__init__.py
darkcoins/base/db/mysql.py
darkcoins/base/drive/__init__.py
darkcoins/base/drive/job.py
darkcoins/base/drive/lanzou.py
darkcoins/base/drive/notecoin.db
darkcoins/base/drive/oss.py
darkcoins/base/drive/transform.py
darkcoins/base/tables/__init__.py
darkcoins/base/tables/kline.py
darkcoins/base/tables/strategy.py
darkcoins/base/tables/trade.py
darkcoins/coins/__init__.py
darkcoins/coins/base/__init__.py
darkcoins/coins/base/file.py
darkcoins/coins/base/load.py
darkcoins/coins/okex/__init__.py
darkcoins/coins/okex/load.py
darkcoins/server/__init__.py
darkcoins/server/download.py
darkcoins/server/notecoin_celery.py
darkcoins/server/notecoin_server.py
darkcoins/server/script.py
darkcoins/server/strategy.py
darkcoins/server/connect/__init__.py
darkcoins/server/connect/base.py
darkcoins/strategy/__init__.py
darkcoins/strategy/binance/__init__.py
darkcoins/strategy/binance/auto.py
darkcoins/strategy/binance/example2.py
darkcoins/strategy/binance/strategy1.py
darkcoins/strategy/binance/strategy2.py
darkcoins/task/__init__.py
darkcoins/task/base.py
darkcoins/task/load.py
darkcoins/utils/__init__.py
darkcoins/utils/log.py
darkcoins/utils/time.py
darkcoins-202303081656.dist-info/LICENSE
darkcoins-202303081656.dist-info/METADATA
darkcoins-202303081656.dist-info/WHEEL
darkcoins-202303081656.dist-info/entry_points.txt
darkcoins-202303081656.dist-info/top_level.txt
darkcoins-202303081656.dist-info/RECORD
