Metadata-Version: 2.1
Name: darkcoins
Version: 202303081656
Summary: darkcoins
Home-page: https://github.com/1007530194
Author: niult
Author-email: 1007530194@qq.com
License-File: LICENSE
Requires-Dist: darkbuild
Requires-Dist: darksecret
